bitcoinshamir/BIP39_List.py
bitcoinshamir/__init__.py
bitcoinshamir/bitcoinshamir.py
bitcoinshamir/decode.py
bitcoinshamir/encode.py
bitcoinshamir/enums.py
bitcoinshamir/exceptions.py
bitcoinshamir/lagrange.py
bitcoinshamir/mnemonic.py
bitcoinshamir/point.py
bitcoinshamir/polynomial.py
bitcoinshamir/share.py
bitcoinshamir/WordLists/chinese_simplified.txt
bitcoinshamir/WordLists/chinese_traditional.txt
bitcoinshamir/WordLists/czech.txt
bitcoinshamir/WordLists/english.txt
bitcoinshamir/WordLists/french.txt
bitcoinshamir/WordLists/italian.txt
bitcoinshamir/WordLists/japanese.txt
bitcoinshamir/WordLists/korean.txt
bitcoinshamir/WordLists/portuguese.txt
bitcoinshamir/WordLists/spanish.txt
bitcoinshamir-1.0.1.dist-info/METADATA
bitcoinshamir-1.0.1.dist-info/WHEEL
bitcoinshamir-1.0.1.dist-info/licenses/LICENSE
bitcoinshamir-1.0.1.dist-info/RECORD
